{
  "/oes/audit/pipelinescount-69" : {
    "transaction" : "/oes/audit/pipelinescount-69",
    "sampleCount" : 1,
    "errorCount" : 0,
    "errorPct" : 0.0,
    "meanResTime" : 1158.0,
    "medianResTime" : 1158.0,
    "minResTime" : 1158.0,
    "maxResTime" : 1158.0,
    "pct1ResTime" : 1158.0,
    "pct2ResTime" : 1158.0,
    "pct3ResTime" : 1158.0,
    "throughput" : 0.8635578583765112,
    "receivedKBytesPerSec" : 0.9268067249568221,
    "sentKBytesPerSec" : 0.3862397452504318
  },
  "/dashboardservice/v1/installation/installationmode-47" : {
    "transaction" : "/dashboardservice/v1/installation/installationmode-47",
    "sampleCount" : 1,
    "errorCount" : 0,
    "errorPct" : 0.0,
    "meanResTime" : 182.0,
    "medianResTime" : 182.0,
    "minResTime" : 182.0,
    "maxResTime" : 182.0,
    "pct1ResTime" : 182.0,
    "pct2ResTime" : 182.0,
    "pct3ResTime" : 182.0,
    "throughput" : 5.4945054945054945,
    "receivedKBytesPerSec" : 4.995492788461538,
    "sentKBytesPerSec" : 2.5916466346153846
  },
  "/auth/user-44" : {
    "transaction" : "/auth/user-44",
    "sampleCount" : 1,
    "errorCount" : 0,
    "errorPct" : 0.0,
    "meanResTime" : 266.0,
    "medianResTime" : 266.0,
    "minResTime" : 266.0,
    "maxResTime" : 266.0,
    "pct1ResTime" : 266.0,
    "pct2ResTime" : 266.0,
    "pct3ResTime" : 266.0,
    "throughput" : 3.7593984962406015,
    "receivedKBytesPerSec" : 4.177925281954887,
    "sentKBytesPerSec" : 1.6263804041353382
  },
  "/autopilot/api/v1/credentials-75" : {
    "transaction" : "/autopilot/api/v1/credentials-75",
    "sampleCount" : 1,
    "errorCount" : 0,
    "errorPct" : 0.0,
    "meanResTime" : 652.0,
    "medianResTime" : 652.0,
    "minResTime" : 652.0,
    "maxResTime" : 652.0,
    "pct1ResTime" : 652.0,
    "pct2ResTime" : 652.0,
    "pct3ResTime" : 652.0,
    "throughput" : 1.5337423312883436,
    "receivedKBytesPerSec" : 1.3704826495398772,
    "sentKBytesPerSec" : 0.7024659700920245
  },
  "/oes/accountsConfig/getAccounts-78" : {
    "transaction" : "/oes/accountsConfig/getAccounts-78",
    "sampleCount" : 1,
    "errorCount" : 0,
    "errorPct" : 0.0,
    "meanResTime" : 208.0,
    "medianResTime" : 208.0,
    "minResTime" : 208.0,
    "maxResTime" : 208.0,
    "pct1ResTime" : 208.0,
    "pct2ResTime" : 208.0,
    "pct3ResTime" : 208.0,
    "throughput" : 4.807692307692308,
    "receivedKBytesPerSec" : 4.972017728365385,
    "sentKBytesPerSec" : 2.201960637019231
  },
  "/oes/accountsConfig/getAccounts-58" : {
    "transaction" : "/oes/accountsConfig/getAccounts-58",
    "sampleCount" : 1,
    "errorCount" : 0,
    "errorPct" : 0.0,
    "meanResTime" : 241.0,
    "medianResTime" : 241.0,
    "minResTime" : 241.0,
    "maxResTime" : 241.0,
    "pct1ResTime" : 241.0,
    "pct2ResTime" : 241.0,
    "pct3ResTime" : 241.0,
    "throughput" : 4.149377593360996,
    "receivedKBytesPerSec" : 3.707695798755187,
    "sentKBytesPerSec" : 1.9247601141078838
  },
  "/autopilot/api/v1/credentials-79" : {
    "transaction" : "/autopilot/api/v1/credentials-79",
    "sampleCount" : 1,
    "errorCount" : 0,
    "errorPct" : 0.0,
    "meanResTime" : 149.0,
    "medianResTime" : 149.0,
    "minResTime" : 149.0,
    "maxResTime" : 149.0,
    "pct1ResTime" : 149.0,
    "pct2ResTime" : 149.0,
    "pct3ResTime" : 149.0,
    "throughput" : 6.7114093959731544,
    "receivedKBytesPerSec" : 5.997011325503356,
    "sentKBytesPerSec" : 3.060769714765101
  },
  "/oes/accountsConfig/getAccounts-74" : {
    "transaction" : "/oes/accountsConfig/getAccounts-74",
    "sampleCount" : 1,
    "errorCount" : 0,
    "errorPct" : 0.0,
    "meanResTime" : 661.0,
    "medianResTime" : 661.0,
    "minResTime" : 661.0,
    "maxResTime" : 661.0,
    "pct1ResTime" : 661.0,
    "pct2ResTime" : 661.0,
    "pct3ResTime" : 661.0,
    "throughput" : 1.5128593040847202,
    "receivedKBytesPerSec" : 1.3518225226928895,
    "sentKBytesPerSec" : 0.6958561838124054
  },
  "/oes/dashboard/widgetRawData-66" : {
    "transaction" : "/oes/dashboard/widgetRawData-66",
    "sampleCount" : 1,
    "errorCount" : 0,
    "errorPct" : 0.0,
    "meanResTime" : 167.0,
    "medianResTime" : 167.0,
    "minResTime" : 167.0,
    "maxResTime" : 167.0,
    "pct1ResTime" : 167.0,
    "pct2ResTime" : 167.0,
    "pct3ResTime" : 167.0,
    "throughput" : 5.9880239520958085,
    "receivedKBytesPerSec" : 6.830089820359281,
    "sentKBytesPerSec" : 2.6957803143712575
  },
  "/oes/policy/endpointType-55" : {
    "transaction" : "/oes/policy/endpointType-55",
    "sampleCount" : 1,
    "errorCount" : 0,
    "errorPct" : 0.0,
    "meanResTime" : 136.0,
    "medianResTime" : 136.0,
    "minResTime" : 136.0,
    "maxResTime" : 136.0,
    "pct1ResTime" : 136.0,
    "pct2ResTime" : 136.0,
    "pct3ResTime" : 136.0,
    "throughput" : 7.352941176470588,
    "receivedKBytesPerSec" : 6.6061580882352935,
    "sentKBytesPerSec" : 3.2815372242647056
  },
  "/auth/user-61" : {
    "transaction" : "/auth/user-61",
    "sampleCount" : 1,
    "errorCount" : 0,
    "errorPct" : 0.0,
    "meanResTime" : 87.0,
    "medianResTime" : 87.0,
    "minResTime" : 87.0,
    "maxResTime" : 87.0,
    "pct1ResTime" : 87.0,
    "pct2ResTime" : 87.0,
    "pct3ResTime" : 87.0,
    "throughput" : 11.494252873563218,
    "receivedKBytesPerSec" : 12.773886494252874,
    "sentKBytesPerSec" : 4.972611350574713
  },
  "/dashboardservice/v1/datasources-68" : {
    "transaction" : "/dashboardservice/v1/datasources-68",
    "sampleCount" : 1,
    "errorCount" : 0,
    "errorPct" : 0.0,
    "meanResTime" : 267.0,
    "medianResTime" : 267.0,
    "minResTime" : 267.0,
    "maxResTime" : 267.0,
    "pct1ResTime" : 267.0,
    "pct2ResTime" : 267.0,
    "pct3ResTime" : 267.0,
    "throughput" : 3.745318352059925,
    "receivedKBytesPerSec" : 6.51407420411985,
    "sentKBytesPerSec" : 1.700754915730337
  },
  "/platformservice/v1/applications-67" : {
    "transaction" : "/platformservice/v1/applications-67",
    "sampleCount" : 1,
    "errorCount" : 0,
    "errorPct" : 0.0,
    "meanResTime" : 262.0,
    "medianResTime" : 262.0,
    "minResTime" : 262.0,
    "maxResTime" : 262.0,
    "pct1ResTime" : 262.0,
    "pct2ResTime" : 262.0,
    "pct3ResTime" : 262.0,
    "throughput" : 3.8167938931297707,
    "receivedKBytesPerSec" : 3.4105140744274807,
    "sentKBytesPerSec" : 1.733212070610687
  },
  "/oes/policy/list-71" : {
    "transaction" : "/oes/policy/list-71",
    "sampleCount" : 1,
    "errorCount" : 0,
    "errorPct" : 0.0,
    "meanResTime" : 259.0,
    "medianResTime" : 259.0,
    "minResTime" : 259.0,
    "maxResTime" : 259.0,
    "pct1ResTime" : 259.0,
    "pct2ResTime" : 259.0,
    "pct3ResTime" : 259.0,
    "throughput" : 3.8610038610038613,
    "receivedKBytesPerSec" : 3.744118001930502,
    "sentKBytesPerSec" : 1.6929597007722008
  },
  "/oes/dashboard/dynamicMenu-46" : {
    "transaction" : "/oes/dashboard/dynamicMenu-46",
    "sampleCount" : 1,
    "errorCount" : 0,
    "errorPct" : 0.0,
    "meanResTime" : 192.0,
    "medianResTime" : 192.0,
    "minResTime" : 192.0,
    "maxResTime" : 192.0,
    "pct1ResTime" : 192.0,
    "pct2ResTime" : 192.0,
    "pct3ResTime" : 192.0,
    "throughput" : 5.208333333333333,
    "receivedKBytesPerSec" : 6.464640299479167,
    "sentKBytesPerSec" : 2.3345947265625
  },
  "/oes/policy/list-54" : {
    "transaction" : "/oes/policy/list-54",
    "sampleCount" : 1,
    "errorCount" : 0,
    "errorPct" : 0.0,
    "meanResTime" : 185.0,
    "medianResTime" : 185.0,
    "minResTime" : 185.0,
    "maxResTime" : 185.0,
    "pct1ResTime" : 185.0,
    "pct2ResTime" : 185.0,
    "pct3ResTime" : 185.0,
    "throughput" : 5.405405405405405,
    "receivedKBytesPerSec" : 5.241765202702703,
    "sentKBytesPerSec" : 2.370143581081081
  },
  "/platformservice/v1/users/user2/usergroups/refresh-62" : {
    "transaction" : "/platformservice/v1/users/user2/usergroups/refresh-62",
    "sampleCount" : 1,
    "errorCount" : 0,
    "errorPct" : 0.0,
    "meanResTime" : 369.0,
    "medianResTime" : 369.0,
    "minResTime" : 369.0,
    "maxResTime" : 369.0,
    "pct1ResTime" : 369.0,
    "pct2ResTime" : 369.0,
    "pct3ResTime" : 369.0,
    "throughput" : 2.710027100271003,
    "receivedKBytesPerSec" : 2.2945248983739837,
    "sentKBytesPerSec" : 1.418529810298103
  },
  "/oes/dashboard/dynamicMenu-63" : {
    "transaction" : "/oes/dashboard/dynamicMenu-63",
    "sampleCount" : 1,
    "errorCount" : 0,
    "errorPct" : 0.0,
    "meanResTime" : 254.0,
    "medianResTime" : 254.0,
    "minResTime" : 254.0,
    "maxResTime" : 254.0,
    "pct1ResTime" : 254.0,
    "pct2ResTime" : 254.0,
    "pct3ResTime" : 254.0,
    "throughput" : 3.937007874015748,
    "receivedKBytesPerSec" : 4.8866572342519685,
    "sentKBytesPerSec" : 1.7647330216535433
  },
  "login and Loading" : {
    "transaction" : "login and Loading",
    "sampleCount" : 1,
    "errorCount" : 0,
    "errorPct" : 0.0,
    "meanResTime" : 11118.0,
    "medianResTime" : 11118.0,
    "minResTime" : 11118.0,
    "maxResTime" : 11118.0,
    "pct1ResTime" : 11118.0,
    "pct2ResTime" : 11118.0,
    "pct3ResTime" : 11118.0,
    "throughput" : 0.08994423457456377,
    "receivedKBytesPerSec" : 1.7754324350152906,
    "sentKBytesPerSec" : 0.5437058711099119
  },
  "/login-59" : {
    "transaction" : "/login-59",
    "sampleCount" : 1,
    "errorCount" : 0,
    "errorPct" : 0.0,
    "meanResTime" : 1596.0,
    "medianResTime" : 1596.0,
    "minResTime" : 1596.0,
    "maxResTime" : 1596.0,
    "pct1ResTime" : 1596.0,
    "pct2ResTime" : 1596.0,
    "pct3ResTime" : 1596.0,
    "throughput" : 0.6265664160401002,
    "receivedKBytesPerSec" : 0.5629307644110275,
    "sentKBytesPerSec" : 0.34448915256892226
  },
  "/dashboardservice/v1/dashboard/user2/applications-48" : {
    "transaction" : "/dashboardservice/v1/dashboard/user2/applications-48",
    "sampleCount" : 1,
    "errorCount" : 0,
    "errorPct" : 0.0,
    "meanResTime" : 306.0,
    "medianResTime" : 306.0,
    "minResTime" : 306.0,
    "maxResTime" : 306.0,
    "pct1ResTime" : 306.0,
    "pct2ResTime" : 306.0,
    "pct3ResTime" : 306.0,
    "throughput" : 3.2679738562091503,
    "receivedKBytesPerSec" : 2.9201133578431375,
    "sentKBytesPerSec" : 1.5382455065359477
  },
  "/dashboardservice/v1/dashboard/user2/applications-65" : {
    "transaction" : "/dashboardservice/v1/dashboard/user2/applications-65",
    "sampleCount" : 1,
    "errorCount" : 0,
    "errorPct" : 0.0,
    "meanResTime" : 208.0,
    "medianResTime" : 208.0,
    "minResTime" : 208.0,
    "maxResTime" : 208.0,
    "pct1ResTime" : 208.0,
    "pct2ResTime" : 208.0,
    "pct3ResTime" : 208.0,
    "throughput" : 4.807692307692308,
    "receivedKBytesPerSec" : 4.295935997596154,
    "sentKBytesPerSec" : 2.262995793269231
  },
  "/platformservice/v1/users/user2/usergroups/refresh-45" : {
    "transaction" : "/platformservice/v1/users/user2/usergroups/refresh-45",
    "sampleCount" : 1,
    "errorCount" : 0,
    "errorPct" : 0.0,
    "meanResTime" : 381.0,
    "medianResTime" : 381.0,
    "minResTime" : 381.0,
    "maxResTime" : 381.0,
    "pct1ResTime" : 381.0,
    "pct2ResTime" : 381.0,
    "pct3ResTime" : 381.0,
    "throughput" : 2.6246719160104988,
    "receivedKBytesPerSec" : 2.2222563976377954,
    "sentKBytesPerSec" : 1.3738517060367454
  },
  "/dashboardservice/v1/installation/installationmode-64" : {
    "transaction" : "/dashboardservice/v1/installation/installationmode-64",
    "sampleCount" : 1,
    "errorCount" : 0,
    "errorPct" : 0.0,
    "meanResTime" : 99.0,
    "medianResTime" : 99.0,
    "minResTime" : 99.0,
    "maxResTime" : 99.0,
    "pct1ResTime" : 99.0,
    "pct2ResTime" : 99.0,
    "pct3ResTime" : 99.0,
    "throughput" : 10.101010101010102,
    "receivedKBytesPerSec" : 9.183633207070706,
    "sentKBytesPerSec" : 4.764441287878788
  },
  "/oes/accountsConfig/saveAccount-77" : {
    "transaction" : "/oes/accountsConfig/saveAccount-77",
    "sampleCount" : 1,
    "errorCount" : 0,
    "errorPct" : 0.0,
    "meanResTime" : 276.0,
    "medianResTime" : 276.0,
    "minResTime" : 276.0,
    "maxResTime" : 276.0,
    "pct1ResTime" : 276.0,
    "pct2ResTime" : 276.0,
    "pct3ResTime" : 276.0,
    "throughput" : 3.6231884057971016,
    "receivedKBytesPerSec" : 3.467504528985507,
    "sentKBytesPerSec" : 2.352949501811594
  },
  "/oes/accountsConfig/saveAccount-76" : {
    "transaction" : "/oes/accountsConfig/saveAccount-76",
    "sampleCount" : 1,
    "errorCount" : 0,
    "errorPct" : 0.0,
    "meanResTime" : 30.0,
    "medianResTime" : 30.0,
    "minResTime" : 30.0,
    "maxResTime" : 30.0,
    "pct1ResTime" : 30.0,
    "pct2ResTime" : 30.0,
    "pct3ResTime" : 30.0,
    "throughput" : 33.333333333333336,
    "receivedKBytesPerSec" : 26.204427083333336,
    "sentKBytesPerSec" : 17.122395833333336
  },
  "/dashboardservice/v1/datasources-51" : {
    "transaction" : "/dashboardservice/v1/datasources-51",
    "sampleCount" : 1,
    "errorCount" : 0,
    "errorPct" : 0.0,
    "meanResTime" : 2356.0,
    "medianResTime" : 2356.0,
    "minResTime" : 2356.0,
    "maxResTime" : 2356.0,
    "pct1ResTime" : 2356.0,
    "pct2ResTime" : 2356.0,
    "pct3ResTime" : 2356.0,
    "throughput" : 0.4244482173174873,
    "receivedKBytesPerSec" : 0.7382248779711376,
    "sentKBytesPerSec" : 0.19274259868421054
  },
  "/oes/audit/pipelinescount-52" : {
    "transaction" : "/oes/audit/pipelinescount-52",
    "sampleCount" : 1,
    "errorCount" : 0,
    "errorPct" : 0.0,
    "meanResTime" : 3630.0,
    "medianResTime" : 3630.0,
    "minResTime" : 3630.0,
    "maxResTime" : 3630.0,
    "pct1ResTime" : 3630.0,
    "pct2ResTime" : 3630.0,
    "pct3ResTime" : 3630.0,
    "throughput" : 0.2754820936639118,
    "receivedKBytesPerSec" : 0.29565900482093666,
    "sentKBytesPerSec" : 0.12321367079889807
  },
  "/oes/audit/pipelineconfig-53" : {
    "transaction" : "/oes/audit/pipelineconfig-53",
    "sampleCount" : 1,
    "errorCount" : 0,
    "errorPct" : 0.0,
    "meanResTime" : 407.0,
    "medianResTime" : 407.0,
    "minResTime" : 407.0,
    "maxResTime" : 407.0,
    "pct1ResTime" : 407.0,
    "pct2ResTime" : 407.0,
    "pct3ResTime" : 407.0,
    "throughput" : 2.457002457002457,
    "receivedKBytesPerSec" : 17.515740171990174,
    "sentKBytesPerSec" : 1.137323402948403
  },
  "/login-42" : {
    "transaction" : "/login-42",
    "sampleCount" : 1,
    "errorCount" : 0,
    "errorPct" : 0.0,
    "meanResTime" : 1613.0,
    "medianResTime" : 1613.0,
    "minResTime" : 1613.0,
    "maxResTime" : 1613.0,
    "pct1ResTime" : 1613.0,
    "pct2ResTime" : 1613.0,
    "pct3ResTime" : 1613.0,
    "throughput" : 0.6199628022318661,
    "receivedKBytesPerSec" : 0.5539706680099195,
    "sentKBytesPerSec" : 0.33783129262244266
  },
  "/oes/dashboard/widgetRawData-49" : {
    "transaction" : "/oes/dashboard/widgetRawData-49",
    "sampleCount" : 1,
    "errorCount" : 0,
    "errorPct" : 0.0,
    "meanResTime" : 532.0,
    "medianResTime" : 532.0,
    "minResTime" : 532.0,
    "maxResTime" : 532.0,
    "pct1ResTime" : 532.0,
    "pct2ResTime" : 532.0,
    "pct3ResTime" : 532.0,
    "throughput" : 1.8796992481203008,
    "receivedKBytesPerSec" : 2.1440319548872178,
    "sentKBytesPerSec" : 0.8462317904135338
  },
  "/platformservice/v1/applications-50" : {
    "transaction" : "/platformservice/v1/applications-50",
    "sampleCount" : 1,
    "errorCount" : 0,
    "errorPct" : 0.0,
    "meanResTime" : 932.0,
    "medianResTime" : 932.0,
    "minResTime" : 932.0,
    "maxResTime" : 932.0,
    "pct1ResTime" : 932.0,
    "pct2ResTime" : 932.0,
    "pct3ResTime" : 932.0,
    "throughput" : 1.0729613733905579,
    "receivedKBytesPerSec" : 0.9587496646995708,
    "sentKBytesPerSec" : 0.48723343615879827
  },
  "Login and Loading" : {
    "transaction" : "Login and Loading",
    "sampleCount" : 1,
    "errorCount" : 0,
    "errorPct" : 0.0,
    "meanResTime" : 6502.0,
    "medianResTime" : 6502.0,
    "minResTime" : 6502.0,
    "maxResTime" : 6502.0,
    "pct1ResTime" : 6502.0,
    "pct2ResTime" : 6502.0,
    "pct3ResTime" : 6502.0,
    "throughput" : 0.15379883112888343,
    "receivedKBytesPerSec" : 3.311481082743771,
    "sentKBytesPerSec" : 1.071635410258382
  },
  "/oes/policy/endpointType-72" : {
    "transaction" : "/oes/policy/endpointType-72",
    "sampleCount" : 1,
    "errorCount" : 0,
    "errorPct" : 0.0,
    "meanResTime" : 240.0,
    "medianResTime" : 240.0,
    "minResTime" : 240.0,
    "maxResTime" : 240.0,
    "pct1ResTime" : 240.0,
    "pct2ResTime" : 240.0,
    "pct3ResTime" : 240.0,
    "throughput" : 4.166666666666667,
    "receivedKBytesPerSec" : 3.7434895833333335,
    "sentKBytesPerSec" : 1.8595377604166667
  },
  "/oes/audit/pipelineconfig-70" : {
    "transaction" : "/oes/audit/pipelineconfig-70",
    "sampleCount" : 1,
    "errorCount" : 0,
    "errorPct" : 0.0,
    "meanResTime" : 223.0,
    "medianResTime" : 223.0,
    "minResTime" : 223.0,
    "maxResTime" : 223.0,
    "pct1ResTime" : 223.0,
    "pct2ResTime" : 223.0,
    "pct3ResTime" : 223.0,
    "throughput" : 4.484304932735426,
    "receivedKBytesPerSec" : 31.96818946188341,
    "sentKBytesPerSec" : 2.0757427130044843
  },
  "/oes/accountsConfig/deleteAccount/?accountName=Jmeter-test-57" : {
    "transaction" : "/oes/accountsConfig/deleteAccount/?accountName=Jmeter-test-57",
    "sampleCount" : 1,
    "errorCount" : 0,
    "errorPct" : 0.0,
    "meanResTime" : 263.0,
    "medianResTime" : 263.0,
    "minResTime" : 263.0,
    "maxResTime" : 263.0,
    "pct1ResTime" : 263.0,
    "pct2ResTime" : 263.0,
    "pct3ResTime" : 263.0,
    "throughput" : 3.802281368821293,
    "receivedKBytesPerSec" : 3.646328422053232,
    "sentKBytesPerSec" : 2.2093334125475286
  },
  "DataSource-Delete" : {
    "transaction" : "DataSource-Delete",
    "sampleCount" : 1,
    "errorCount" : 0,
    "errorPct" : 0.0,
    "meanResTime" : 504.0,
    "medianResTime" : 504.0,
    "minResTime" : 504.0,
    "maxResTime" : 504.0,
    "pct1ResTime" : 504.0,
    "pct2ResTime" : 504.0,
    "pct3ResTime" : 504.0,
    "throughput" : 1.984126984126984,
    "receivedKBytesPerSec" : 3.6756727430555554,
    "sentKBytesPerSec" : 2.0732576884920633
  },
  "Total" : {
    "transaction" : "Total",
    "sampleCount" : 34,
    "errorCount" : 0,
    "errorPct" : 0.0,
    "meanResTime" : 552.5588235294117,
    "medianResTime" : 262.5,
    "minResTime" : 30.0,
    "maxResTime" : 3630.0,
    "pct1ResTime" : 1604.5,
    "pct2ResTime" : 2674.5,
    "pct3ResTime" : 3630.0,
    "throughput" : 1.203028801924846,
    "receivedKBytesPerSec" : 1.6557195284304012,
    "sentKBytesPerSec" : 0.5708996399759394
  },
  "DataSouce create and save" : {
    "transaction" : "DataSouce create and save",
    "sampleCount" : 1,
    "errorCount" : 0,
    "errorPct" : 0.0,
    "meanResTime" : 663.0,
    "medianResTime" : 663.0,
    "minResTime" : 663.0,
    "maxResTime" : 663.0,
    "pct1ResTime" : 663.0,
    "pct2ResTime" : 663.0,
    "pct3ResTime" : 663.0,
    "throughput" : 1.5082956259426847,
    "receivedKBytesPerSec" : 5.536800056561086,
    "sentKBytesPerSec" : 3.132953902714932
  }
}