{
  "/oes/audit/pipelinescount-69" : {
    "transaction" : "/oes/audit/pipelinescount-69",
    "sampleCount" : 1,
    "errorCount" : 0,
    "errorPct" : 0.0,
    "meanResTime" : 4687.0,
    "medianResTime" : 4687.0,
    "minResTime" : 4687.0,
    "maxResTime" : 4687.0,
    "pct1ResTime" : 4687.0,
    "pct2ResTime" : 4687.0,
    "pct3ResTime" : 4687.0,
    "throughput" : 0.2133560913164071,
    "receivedKBytesPerSec" : 0.20377173565180284,
    "sentKBytesPerSec" : 0.09938560113078727
  },
  "" : {
    "transaction" : "",
    "sampleCount" : 7,
    "errorCount" : 7,
    "errorPct" : 100.0,
    "meanResTime" : 139.14285714285717,
    "medianResTime" : 90.0,
    "minResTime" : 18.0,
    "maxResTime" : 492.0,
    "pct1ResTime" : 492.0,
    "pct2ResTime" : 492.0,
    "pct3ResTime" : 492.0,
    "throughput" : 4.260499087035909,
    "receivedKBytesPerSec" : 13.456710286062082,
    "sentKBytesPerSec" : 14.36789124315277
  },
  "/dashboardservice/v1/dashboard//applications-129" : {
    "transaction" : "/dashboardservice/v1/dashboard//applications-129",
    "sampleCount" : 1,
    "errorCount" : 1,
    "errorPct" : 100.0,
    "meanResTime" : 10.0,
    "medianResTime" : 10.0,
    "minResTime" : 10.0,
    "maxResTime" : 10.0,
    "pct1ResTime" : 10.0,
    "pct2ResTime" : 10.0,
    "pct3ResTime" : 10.0,
    "throughput" : 100.0,
    "receivedKBytesPerSec" : 40.91796875,
    "sentKBytesPerSec" : 45.3125
  },
  "/autopilot/api/v1/credentials-75" : {
    "transaction" : "/autopilot/api/v1/credentials-75",
    "sampleCount" : 1,
    "errorCount" : 0,
    "errorPct" : 0.0,
    "meanResTime" : 38.0,
    "medianResTime" : 38.0,
    "minResTime" : 38.0,
    "maxResTime" : 38.0,
    "pct1ResTime" : 38.0,
    "pct2ResTime" : 38.0,
    "pct3ResTime" : 38.0,
    "throughput" : 26.31578947368421,
    "receivedKBytesPerSec" : 20.379317434210527,
    "sentKBytesPerSec" : 12.541118421052632
  },
  "/autopilot/api/v1/defaultLogTemplate-109" : {
    "transaction" : "/autopilot/api/v1/defaultLogTemplate-109",
    "sampleCount" : 1,
    "errorCount" : 1,
    "errorPct" : 100.0,
    "meanResTime" : 19.0,
    "medianResTime" : 19.0,
    "minResTime" : 19.0,
    "maxResTime" : 19.0,
    "pct1ResTime" : 19.0,
    "pct2ResTime" : 19.0,
    "pct3ResTime" : 19.0,
    "throughput" : 52.63157894736842,
    "receivedKBytesPerSec" : 21.53577302631579,
    "sentKBytesPerSec" : 22.56373355263158
  },
  "/autopilot/api/v1/credentials-79" : {
    "transaction" : "/autopilot/api/v1/credentials-79",
    "sampleCount" : 1,
    "errorCount" : 0,
    "errorPct" : 0.0,
    "meanResTime" : 36.0,
    "medianResTime" : 36.0,
    "minResTime" : 36.0,
    "maxResTime" : 36.0,
    "pct1ResTime" : 36.0,
    "pct2ResTime" : 36.0,
    "pct3ResTime" : 36.0,
    "throughput" : 27.777777777777775,
    "receivedKBytesPerSec" : 21.511501736111114,
    "sentKBytesPerSec" : 13.183593750000002
  },
  "/oes/accountsConfig/getAccounts-53" : {
    "transaction" : "/oes/accountsConfig/getAccounts-53",
    "sampleCount" : 1,
    "errorCount" : 1,
    "errorPct" : 100.0,
    "meanResTime" : 15.0,
    "medianResTime" : 15.0,
    "minResTime" : 15.0,
    "maxResTime" : 15.0,
    "pct1ResTime" : 15.0,
    "pct2ResTime" : 15.0,
    "pct3ResTime" : 15.0,
    "throughput" : 66.66666666666667,
    "receivedKBytesPerSec" : 27.278645833333336,
    "sentKBytesPerSec" : 28.125
  },
  "/oes/policy/endpointType-55" : {
    "transaction" : "/oes/policy/endpointType-55",
    "sampleCount" : 1,
    "errorCount" : 0,
    "errorPct" : 0.0,
    "meanResTime" : 14.0,
    "medianResTime" : 14.0,
    "minResTime" : 14.0,
    "maxResTime" : 14.0,
    "pct1ResTime" : 14.0,
    "pct2ResTime" : 14.0,
    "pct3ResTime" : 14.0,
    "throughput" : 71.42857142857143,
    "receivedKBytesPerSec" : 55.6640625,
    "sentKBytesPerSec" : 33.203125
  },
  "/oes/policy/list-71" : {
    "transaction" : "/oes/policy/list-71",
    "sampleCount" : 1,
    "errorCount" : 0,
    "errorPct" : 0.0,
    "meanResTime" : 70.0,
    "medianResTime" : 70.0,
    "minResTime" : 70.0,
    "maxResTime" : 70.0,
    "pct1ResTime" : 70.0,
    "pct2ResTime" : 70.0,
    "pct3ResTime" : 70.0,
    "throughput" : 14.285714285714285,
    "receivedKBytesPerSec" : 12.151227678571427,
    "sentKBytesPerSec" : 6.529017857142857
  },
  "/dashboardservice/v1/application-128" : {
    "transaction" : "/dashboardservice/v1/application-128",
    "sampleCount" : 1,
    "errorCount" : 1,
    "errorPct" : 100.0,
    "meanResTime" : 8.0,
    "medianResTime" : 8.0,
    "minResTime" : 8.0,
    "maxResTime" : 8.0,
    "pct1ResTime" : 8.0,
    "pct2ResTime" : 8.0,
    "pct3ResTime" : 8.0,
    "throughput" : 125.0,
    "receivedKBytesPerSec" : 51.1474609375,
    "sentKBytesPerSec" : 117.7978515625
  },
  "/oes/policy/endpointType-101" : {
    "transaction" : "/oes/policy/endpointType-101",
    "sampleCount" : 1,
    "errorCount" : 1,
    "errorPct" : 100.0,
    "meanResTime" : 11.0,
    "medianResTime" : 11.0,
    "minResTime" : 11.0,
    "maxResTime" : 11.0,
    "pct1ResTime" : 11.0,
    "pct2ResTime" : 11.0,
    "pct3ResTime" : 11.0,
    "throughput" : 90.9090909090909,
    "receivedKBytesPerSec" : 37.198153409090914,
    "sentKBytesPerSec" : 37.109375
  },
  "/dashboardservice/v1/application-127" : {
    "transaction" : "/dashboardservice/v1/application-127",
    "sampleCount" : 1,
    "errorCount" : 1,
    "errorPct" : 100.0,
    "meanResTime" : 12.0,
    "medianResTime" : 12.0,
    "minResTime" : 12.0,
    "maxResTime" : 12.0,
    "pct1ResTime" : 12.0,
    "pct2ResTime" : 12.0,
    "pct3ResTime" : 12.0,
    "throughput" : 83.33333333333333,
    "receivedKBytesPerSec" : 34.098307291666664,
    "sentKBytesPerSec" : 40.0390625
  },
  "/oes/dashboard/applications/17/releases/newRelease-330" : {
    "transaction" : "/oes/dashboard/applications/17/releases/newRelease-330",
    "sampleCount" : 1,
    "errorCount" : 1,
    "errorPct" : 100.0,
    "meanResTime" : 19.0,
    "medianResTime" : 19.0,
    "minResTime" : 19.0,
    "maxResTime" : 19.0,
    "pct1ResTime" : 19.0,
    "pct2ResTime" : 19.0,
    "pct3ResTime" : 19.0,
    "throughput" : 52.63157894736842,
    "receivedKBytesPerSec" : 21.53577302631579,
    "sentKBytesPerSec" : 26.212993421052634
  },
  "/oes/accountsConfig/deleteAccount/?accountName=Jmeter-test-50-1" : {
    "transaction" : "/oes/accountsConfig/deleteAccount/?accountName=Jmeter-test-50-1",
    "sampleCount" : 1,
    "errorCount" : 0,
    "errorPct" : 0.0,
    "meanResTime" : 29.0,
    "medianResTime" : 29.0,
    "minResTime" : 29.0,
    "maxResTime" : 29.0,
    "pct1ResTime" : 29.0,
    "pct2ResTime" : 29.0,
    "pct3ResTime" : 29.0,
    "throughput" : 34.48275862068965,
    "receivedKBytesPerSec" : 47.81788793103448,
    "sentKBytesPerSec" : 15.557650862068964
  },
  "/oes/dashboard/applications/17/releases/newRelease-331" : {
    "transaction" : "/oes/dashboard/applications/17/releases/newRelease-331",
    "sampleCount" : 1,
    "errorCount" : 1,
    "errorPct" : 100.0,
    "meanResTime" : 9.0,
    "medianResTime" : 9.0,
    "minResTime" : 9.0,
    "maxResTime" : 9.0,
    "pct1ResTime" : 9.0,
    "pct2ResTime" : 9.0,
    "pct3ResTime" : 9.0,
    "throughput" : 111.1111111111111,
    "receivedKBytesPerSec" : 45.46440972222223,
    "sentKBytesPerSec" : 70.20399305555556
  },
  "/oes/accountsConfig/deleteAccount/?accountName=Jmeter-test-50-0" : {
    "transaction" : "/oes/accountsConfig/deleteAccount/?accountName=Jmeter-test-50-0",
    "sampleCount" : 1,
    "errorCount" : 0,
    "errorPct" : 0.0,
    "meanResTime" : 27.0,
    "medianResTime" : 27.0,
    "minResTime" : 27.0,
    "maxResTime" : 27.0,
    "pct1ResTime" : 27.0,
    "pct2ResTime" : 27.0,
    "pct3ResTime" : 27.0,
    "throughput" : 37.03703703703704,
    "receivedKBytesPerSec" : 29.694733796296298,
    "sentKBytesPerSec" : 19.31423611111111
  },
  "/oes/accountsConfig/getAccounts-111" : {
    "transaction" : "/oes/accountsConfig/getAccounts-111",
    "sampleCount" : 1,
    "errorCount" : 1,
    "errorPct" : 100.0,
    "meanResTime" : 9.0,
    "medianResTime" : 9.0,
    "minResTime" : 9.0,
    "maxResTime" : 9.0,
    "pct1ResTime" : 9.0,
    "pct2ResTime" : 9.0,
    "pct3ResTime" : 9.0,
    "throughput" : 111.1111111111111,
    "receivedKBytesPerSec" : 45.46440972222223,
    "sentKBytesPerSec" : 47.09201388888889
  },
  "/oes/dashboard/widgetRawData-95" : {
    "transaction" : "/oes/dashboard/widgetRawData-95",
    "sampleCount" : 1,
    "errorCount" : 1,
    "errorPct" : 100.0,
    "meanResTime" : 2.0,
    "medianResTime" : 2.0,
    "minResTime" : 2.0,
    "maxResTime" : 2.0,
    "pct1ResTime" : 2.0,
    "pct2ResTime" : 2.0,
    "pct3ResTime" : 2.0,
    "throughput" : 500.0,
    "receivedKBytesPerSec" : 204.58984375,
    "sentKBytesPerSec" : 206.0546875
  },
  "/oes/appOnboarding/pipelineTemplates-108" : {
    "transaction" : "/oes/appOnboarding/pipelineTemplates-108",
    "sampleCount" : 1,
    "errorCount" : 1,
    "errorPct" : 100.0,
    "meanResTime" : 13.0,
    "medianResTime" : 13.0,
    "minResTime" : 13.0,
    "maxResTime" : 13.0,
    "pct1ResTime" : 13.0,
    "pct2ResTime" : 13.0,
    "pct3ResTime" : 13.0,
    "throughput" : 76.92307692307693,
    "receivedKBytesPerSec" : 31.475360576923077,
    "sentKBytesPerSec" : 32.97776442307693
  },
  "/dashboardservice/v1/datasources-97" : {
    "transaction" : "/dashboardservice/v1/datasources-97",
    "sampleCount" : 1,
    "errorCount" : 1,
    "errorPct" : 100.0,
    "meanResTime" : 5.0,
    "medianResTime" : 5.0,
    "minResTime" : 5.0,
    "maxResTime" : 5.0,
    "pct1ResTime" : 5.0,
    "pct2ResTime" : 5.0,
    "pct3ResTime" : 5.0,
    "throughput" : 200.0,
    "receivedKBytesPerSec" : 81.8359375,
    "sentKBytesPerSec" : 83.203125
  },
  "/auth/user-91" : {
    "transaction" : "/auth/user-91",
    "sampleCount" : 1,
    "errorCount" : 1,
    "errorPct" : 100.0,
    "meanResTime" : 15.0,
    "medianResTime" : 15.0,
    "minResTime" : 15.0,
    "maxResTime" : 15.0,
    "pct1ResTime" : 15.0,
    "pct2ResTime" : 15.0,
    "pct3ResTime" : 15.0,
    "throughput" : 66.66666666666667,
    "receivedKBytesPerSec" : 27.278645833333336,
    "sentKBytesPerSec" : 26.302083333333336
  },
  "/oes/dashboard/applications/17/releases/newRelease-329" : {
    "transaction" : "/oes/dashboard/applications/17/releases/newRelease-329",
    "sampleCount" : 1,
    "errorCount" : 1,
    "errorPct" : 100.0,
    "meanResTime" : 19.0,
    "medianResTime" : 19.0,
    "minResTime" : 19.0,
    "maxResTime" : 19.0,
    "pct1ResTime" : 19.0,
    "pct2ResTime" : 19.0,
    "pct3ResTime" : 19.0,
    "throughput" : 52.63157894736842,
    "receivedKBytesPerSec" : 21.53577302631579,
    "sentKBytesPerSec" : 23.283305921052634
  },
  "/oes/policy/endpointType-72" : {
    "transaction" : "/oes/policy/endpointType-72",
    "sampleCount" : 1,
    "errorCount" : 0,
    "errorPct" : 0.0,
    "meanResTime" : 57.0,
    "medianResTime" : 57.0,
    "minResTime" : 57.0,
    "maxResTime" : 57.0,
    "pct1ResTime" : 57.0,
    "pct2ResTime" : 57.0,
    "pct3ResTime" : 57.0,
    "throughput" : 17.543859649122805,
    "receivedKBytesPerSec" : 13.671875,
    "sentKBytesPerSec" : 8.15515350877193
  },
  "/oes/audit/pipelineconfig-70" : {
    "transaction" : "/oes/audit/pipelineconfig-70",
    "sampleCount" : 1,
    "errorCount" : 0,
    "errorPct" : 0.0,
    "meanResTime" : 157.0,
    "medianResTime" : 157.0,
    "minResTime" : 157.0,
    "maxResTime" : 157.0,
    "pct1ResTime" : 157.0,
    "pct2ResTime" : 157.0,
    "pct3ResTime" : 157.0,
    "throughput" : 6.369426751592357,
    "receivedKBytesPerSec" : 48.591759554140125,
    "sentKBytesPerSec" : 3.066530652866242
  },
  "/login-89" : {
    "transaction" : "/login-89",
    "sampleCount" : 1,
    "errorCount" : 1,
    "errorPct" : 100.0,
    "meanResTime" : 201.0,
    "medianResTime" : 201.0,
    "minResTime" : 201.0,
    "maxResTime" : 201.0,
    "pct1ResTime" : 201.0,
    "pct2ResTime" : 201.0,
    "pct3ResTime" : 201.0,
    "throughput" : 4.975124378109452,
    "receivedKBytesPerSec" : 2.0357198383084576,
    "sentKBytesPerSec" : 2.7742148631840795
  },
  "DataSource-Delete" : {
    "transaction" : "DataSource-Delete",
    "sampleCount" : 1,
    "errorCount" : 0,
    "errorPct" : 0.0,
    "meanResTime" : 137.0,
    "medianResTime" : 137.0,
    "minResTime" : 137.0,
    "maxResTime" : 137.0,
    "pct1ResTime" : 137.0,
    "pct2ResTime" : 137.0,
    "pct3ResTime" : 137.0,
    "throughput" : 7.299270072992701,
    "receivedKBytesPerSec" : 31.321281934306565,
    "sentKBytesPerSec" : 12.823619981751824
  },
  "DataSouce create and save" : {
    "transaction" : "DataSouce create and save",
    "sampleCount" : 1,
    "errorCount" : 1,
    "errorPct" : 100.0,
    "meanResTime" : 146.0,
    "medianResTime" : 146.0,
    "minResTime" : 146.0,
    "maxResTime" : 146.0,
    "pct1ResTime" : 146.0,
    "pct2ResTime" : 146.0,
    "pct3ResTime" : 146.0,
    "throughput" : 6.8493150684931505,
    "receivedKBytesPerSec" : 24.18664383561644,
    "sentKBytesPerSec" : 14.73539169520548
  },
  "/oes/accountsConfig/getAccounts-105" : {
    "transaction" : "/oes/accountsConfig/getAccounts-105",
    "sampleCount" : 1,
    "errorCount" : 1,
    "errorPct" : 100.0,
    "meanResTime" : 11.0,
    "medianResTime" : 11.0,
    "minResTime" : 11.0,
    "maxResTime" : 11.0,
    "pct1ResTime" : 11.0,
    "pct2ResTime" : 11.0,
    "pct3ResTime" : 11.0,
    "throughput" : 90.9090909090909,
    "receivedKBytesPerSec" : 37.198153409090914,
    "sentKBytesPerSec" : 38.52982954545455
  },
  "/autopilot/api/v1/credentials-113" : {
    "transaction" : "/autopilot/api/v1/credentials-113",
    "sampleCount" : 1,
    "errorCount" : 1,
    "errorPct" : 100.0,
    "meanResTime" : 26.0,
    "medianResTime" : 26.0,
    "minResTime" : 26.0,
    "maxResTime" : 26.0,
    "pct1ResTime" : 26.0,
    "pct2ResTime" : 26.0,
    "pct3ResTime" : 26.0,
    "throughput" : 38.46153846153847,
    "receivedKBytesPerSec" : 15.737680288461538,
    "sentKBytesPerSec" : 16.22596153846154
  },
  "/dashboardservice/v1/installation/installationmode-93" : {
    "transaction" : "/dashboardservice/v1/installation/installationmode-93",
    "sampleCount" : 1,
    "errorCount" : 1,
    "errorPct" : 100.0,
    "meanResTime" : 10.0,
    "medianResTime" : 10.0,
    "minResTime" : 10.0,
    "maxResTime" : 10.0,
    "pct1ResTime" : 10.0,
    "pct2ResTime" : 10.0,
    "pct3ResTime" : 10.0,
    "throughput" : 100.0,
    "receivedKBytesPerSec" : 40.91796875,
    "sentKBytesPerSec" : 43.359375
  },
  "/autopilot/api/v1/credentials-54" : {
    "transaction" : "/autopilot/api/v1/credentials-54",
    "sampleCount" : 1,
    "errorCount" : 1,
    "errorPct" : 100.0,
    "meanResTime" : 23.0,
    "medianResTime" : 23.0,
    "minResTime" : 23.0,
    "maxResTime" : 23.0,
    "pct1ResTime" : 23.0,
    "pct2ResTime" : 23.0,
    "pct3ResTime" : 23.0,
    "throughput" : 43.47826086956522,
    "receivedKBytesPerSec" : 17.790421195652176,
    "sentKBytesPerSec" : 18.257472826086957
  },
  "/dashboardservice/v1/installation/installationmode-47" : {
    "transaction" : "/dashboardservice/v1/installation/installationmode-47",
    "sampleCount" : 1,
    "errorCount" : 0,
    "errorPct" : 0.0,
    "meanResTime" : 30.0,
    "medianResTime" : 30.0,
    "minResTime" : 30.0,
    "maxResTime" : 30.0,
    "pct1ResTime" : 30.0,
    "pct2ResTime" : 30.0,
    "pct3ResTime" : 30.0,
    "throughput" : 33.333333333333336,
    "receivedKBytesPerSec" : 26.334635416666668,
    "sentKBytesPerSec" : 16.341145833333336
  },
  "/dashboardservice/v1/applications/14-102" : {
    "transaction" : "/dashboardservice/v1/applications/14-102",
    "sampleCount" : 1,
    "errorCount" : 1,
    "errorPct" : 100.0,
    "meanResTime" : 16.0,
    "medianResTime" : 16.0,
    "minResTime" : 16.0,
    "maxResTime" : 16.0,
    "pct1ResTime" : 16.0,
    "pct2ResTime" : 16.0,
    "pct3ResTime" : 16.0,
    "throughput" : 62.5,
    "receivedKBytesPerSec" : 25.57373046875,
    "sentKBytesPerSec" : 26.2451171875
  },
  "/oes/accountsConfig/deleteAccount/?accountName=Jmeter-test-50" : {
    "transaction" : "/oes/accountsConfig/deleteAccount/?accountName=Jmeter-test-50",
    "sampleCount" : 1,
    "errorCount" : 0,
    "errorPct" : 0.0,
    "meanResTime" : 65.0,
    "medianResTime" : 65.0,
    "minResTime" : 65.0,
    "maxResTime" : 65.0,
    "pct1ResTime" : 65.0,
    "pct2ResTime" : 65.0,
    "pct3ResTime" : 65.0,
    "throughput" : 15.384615384615385,
    "receivedKBytesPerSec" : 33.66887019230769,
    "sentKBytesPerSec" : 14.963942307692307
  },
  "/autopilot/api/v1/credentials-51" : {
    "transaction" : "/autopilot/api/v1/credentials-51",
    "sampleCount" : 1,
    "errorCount" : 1,
    "errorPct" : 100.0,
    "meanResTime" : 21.0,
    "medianResTime" : 21.0,
    "minResTime" : 21.0,
    "maxResTime" : 21.0,
    "pct1ResTime" : 21.0,
    "pct2ResTime" : 21.0,
    "pct3ResTime" : 21.0,
    "throughput" : 47.61904761904761,
    "receivedKBytesPerSec" : 19.484747023809522,
    "sentKBytesPerSec" : 19.99627976190476
  },
  "/oes/dashboard/dynamicMenu-46" : {
    "transaction" : "/oes/dashboard/dynamicMenu-46",
    "sampleCount" : 1,
    "errorCount" : 0,
    "errorPct" : 0.0,
    "meanResTime" : 57.0,
    "medianResTime" : 57.0,
    "minResTime" : 57.0,
    "maxResTime" : 57.0,
    "pct1ResTime" : 57.0,
    "pct2ResTime" : 57.0,
    "pct3ResTime" : 57.0,
    "throughput" : 17.543859649122805,
    "receivedKBytesPerSec" : 19.685444078947366,
    "sentKBytesPerSec" : 8.189418859649123
  },
  "/oes/policy/list-54" : {
    "transaction" : "/oes/policy/list-54",
    "sampleCount" : 1,
    "errorCount" : 0,
    "errorPct" : 0.0,
    "meanResTime" : 48.0,
    "medianResTime" : 48.0,
    "minResTime" : 48.0,
    "maxResTime" : 48.0,
    "pct1ResTime" : 48.0,
    "pct2ResTime" : 48.0,
    "pct3ResTime" : 48.0,
    "throughput" : 20.833333333333332,
    "receivedKBytesPerSec" : 17.720540364583332,
    "sentKBytesPerSec" : 9.521484375
  },
  "/oes/accountsConfig/getDockerAccounts-134" : {
    "transaction" : "/oes/accountsConfig/getDockerAccounts-134",
    "sampleCount" : 1,
    "errorCount" : 1,
    "errorPct" : 100.0,
    "meanResTime" : 19.0,
    "medianResTime" : 19.0,
    "minResTime" : 19.0,
    "maxResTime" : 19.0,
    "pct1ResTime" : 19.0,
    "pct2ResTime" : 19.0,
    "pct3ResTime" : 19.0,
    "throughput" : 52.63157894736842,
    "receivedKBytesPerSec" : 21.53577302631579,
    "sentKBytesPerSec" : 22.61513157894737
  },
  "/oes/accountsConfig/getDockerAccounts-136" : {
    "transaction" : "/oes/accountsConfig/getDockerAccounts-136",
    "sampleCount" : 1,
    "errorCount" : 1,
    "errorPct" : 100.0,
    "meanResTime" : 11.0,
    "medianResTime" : 11.0,
    "minResTime" : 11.0,
    "maxResTime" : 11.0,
    "pct1ResTime" : 11.0,
    "pct2ResTime" : 11.0,
    "pct3ResTime" : 11.0,
    "throughput" : 90.9090909090909,
    "receivedKBytesPerSec" : 37.198153409090914,
    "sentKBytesPerSec" : 38.26349431818182
  },
  "/oes/accountsConfig/getAccounts-137" : {
    "transaction" : "/oes/accountsConfig/getAccounts-137",
    "sampleCount" : 1,
    "errorCount" : 1,
    "errorPct" : 100.0,
    "meanResTime" : 18.0,
    "medianResTime" : 18.0,
    "minResTime" : 18.0,
    "maxResTime" : 18.0,
    "pct1ResTime" : 18.0,
    "pct2ResTime" : 18.0,
    "pct3ResTime" : 18.0,
    "throughput" : 55.55555555555555,
    "receivedKBytesPerSec" : 22.732204861111114,
    "sentKBytesPerSec" : 23.057725694444446
  },
  "/dashboardservice/v1/dashboard/user2/applications-65" : {
    "transaction" : "/dashboardservice/v1/dashboard/user2/applications-65",
    "sampleCount" : 1,
    "errorCount" : 0,
    "errorPct" : 0.0,
    "meanResTime" : 345.0,
    "medianResTime" : 345.0,
    "minResTime" : 345.0,
    "maxResTime" : 345.0,
    "pct1ResTime" : 345.0,
    "pct2ResTime" : 345.0,
    "pct3ResTime" : 345.0,
    "throughput" : 2.898550724637681,
    "receivedKBytesPerSec" : 3.6911231884057973,
    "sentKBytesPerSec" : 1.418138586956522
  },
  "/oes/policy/list-100" : {
    "transaction" : "/oes/policy/list-100",
    "sampleCount" : 1,
    "errorCount" : 1,
    "errorPct" : 100.0,
    "meanResTime" : 33.0,
    "medianResTime" : 33.0,
    "minResTime" : 33.0,
    "maxResTime" : 33.0,
    "pct1ResTime" : 33.0,
    "pct2ResTime" : 33.0,
    "pct3ResTime" : 33.0,
    "throughput" : 30.303030303030305,
    "receivedKBytesPerSec" : 12.399384469696969,
    "sentKBytesPerSec" : 12.133049242424242
  },
  "/autopilot/api/v1/credentials-106" : {
    "transaction" : "/autopilot/api/v1/credentials-106",
    "sampleCount" : 1,
    "errorCount" : 1,
    "errorPct" : 100.0,
    "meanResTime" : 10.0,
    "medianResTime" : 10.0,
    "minResTime" : 10.0,
    "maxResTime" : 10.0,
    "pct1ResTime" : 10.0,
    "pct2ResTime" : 10.0,
    "pct3ResTime" : 10.0,
    "throughput" : 100.0,
    "receivedKBytesPerSec" : 40.91796875,
    "sentKBytesPerSec" : 42.1875
  },
  "/oes/accountsConfig/getAccounts-133" : {
    "transaction" : "/oes/accountsConfig/getAccounts-133",
    "sampleCount" : 1,
    "errorCount" : 1,
    "errorPct" : 100.0,
    "meanResTime" : 16.0,
    "medianResTime" : 16.0,
    "minResTime" : 16.0,
    "maxResTime" : 16.0,
    "pct1ResTime" : 16.0,
    "pct2ResTime" : 16.0,
    "pct3ResTime" : 16.0,
    "throughput" : 62.5,
    "receivedKBytesPerSec" : 25.57373046875,
    "sentKBytesPerSec" : 26.4892578125
  },
  "/oes/accountsConfig/getAccounts-49" : {
    "transaction" : "/oes/accountsConfig/getAccounts-49",
    "sampleCount" : 1,
    "errorCount" : 1,
    "errorPct" : 100.0,
    "meanResTime" : 10.0,
    "medianResTime" : 10.0,
    "minResTime" : 10.0,
    "maxResTime" : 10.0,
    "pct1ResTime" : 10.0,
    "pct2ResTime" : 10.0,
    "pct3ResTime" : 10.0,
    "throughput" : 100.0,
    "receivedKBytesPerSec" : 40.91796875,
    "sentKBytesPerSec" : 42.1875
  },
  "/autopilot/api/v1/credentials-47" : {
    "transaction" : "/autopilot/api/v1/credentials-47",
    "sampleCount" : 1,
    "errorCount" : 1,
    "errorPct" : 100.0,
    "meanResTime" : 14.0,
    "medianResTime" : 14.0,
    "minResTime" : 14.0,
    "maxResTime" : 14.0,
    "pct1ResTime" : 14.0,
    "pct2ResTime" : 14.0,
    "pct3ResTime" : 14.0,
    "throughput" : 71.42857142857143,
    "receivedKBytesPerSec" : 29.227120535714285,
    "sentKBytesPerSec" : 29.994419642857142
  },
  "/oes/accountsConfig/getAccounts-46" : {
    "transaction" : "/oes/accountsConfig/getAccounts-46",
    "sampleCount" : 1,
    "errorCount" : 1,
    "errorPct" : 100.0,
    "meanResTime" : 11.0,
    "medianResTime" : 11.0,
    "minResTime" : 11.0,
    "maxResTime" : 11.0,
    "pct1ResTime" : 11.0,
    "pct2ResTime" : 11.0,
    "pct3ResTime" : 11.0,
    "throughput" : 90.9090909090909,
    "receivedKBytesPerSec" : 37.198153409090914,
    "sentKBytesPerSec" : 38.35227272727273
  },
  "/oes/accountsConfig/getAccounts-48" : {
    "transaction" : "/oes/accountsConfig/getAccounts-48",
    "sampleCount" : 1,
    "errorCount" : 0,
    "errorPct" : 0.0,
    "meanResTime" : 72.0,
    "medianResTime" : 72.0,
    "minResTime" : 72.0,
    "maxResTime" : 72.0,
    "pct1ResTime" : 72.0,
    "pct2ResTime" : 72.0,
    "pct3ResTime" : 72.0,
    "throughput" : 13.888888888888888,
    "receivedKBytesPerSec" : 29.201931423611114,
    "sentKBytesPerSec" : 10.891384548611112
  },
  "/oes/audit/pipelinescount-52" : {
    "transaction" : "/oes/audit/pipelinescount-52",
    "sampleCount" : 1,
    "errorCount" : 0,
    "errorPct" : 0.0,
    "meanResTime" : 4259.0,
    "medianResTime" : 4259.0,
    "minResTime" : 4259.0,
    "maxResTime" : 4259.0,
    "pct1ResTime" : 4259.0,
    "pct2ResTime" : 4259.0,
    "pct3ResTime" : 4259.0,
    "throughput" : 0.23479690068091102,
    "receivedKBytesPerSec" : 0.22424938365813568,
    "sentKBytesPerSec" : 0.10937316564921343
  },
  "/oes/audit/pipelineconfig-53" : {
    "transaction" : "/oes/audit/pipelineconfig-53",
    "sampleCount" : 1,
    "errorCount" : 0,
    "errorPct" : 0.0,
    "meanResTime" : 122.0,
    "medianResTime" : 122.0,
    "minResTime" : 122.0,
    "maxResTime" : 122.0,
    "pct1ResTime" : 122.0,
    "pct2ResTime" : 122.0,
    "pct3ResTime" : 122.0,
    "throughput" : 8.196721311475411,
    "receivedKBytesPerSec" : 62.572041495901644,
    "sentKBytesPerSec" : 3.9462730532786887
  },
  "/oes/dashboard/applications/17/releases-332" : {
    "transaction" : "/oes/dashboard/applications/17/releases-332",
    "sampleCount" : 1,
    "errorCount" : 1,
    "errorPct" : 100.0,
    "meanResTime" : 9.0,
    "medianResTime" : 9.0,
    "minResTime" : 9.0,
    "maxResTime" : 9.0,
    "pct1ResTime" : 9.0,
    "pct2ResTime" : 9.0,
    "pct3ResTime" : 9.0,
    "throughput" : 111.1111111111111,
    "receivedKBytesPerSec" : 45.46440972222223,
    "sentKBytesPerSec" : 47.96006944444445
  },
  "/oes/accountsConfig/getAccounts-40" : {
    "transaction" : "/oes/accountsConfig/getAccounts-40",
    "sampleCount" : 1,
    "errorCount" : 1,
    "errorPct" : 100.0,
    "meanResTime" : 9.0,
    "medianResTime" : 9.0,
    "minResTime" : 9.0,
    "maxResTime" : 9.0,
    "pct1ResTime" : 9.0,
    "pct2ResTime" : 9.0,
    "pct3ResTime" : 9.0,
    "throughput" : 111.1111111111111,
    "receivedKBytesPerSec" : 45.46440972222223,
    "sentKBytesPerSec" : 46.875
  },
  "/platformservice/v1/users//applications-96" : {
    "transaction" : "/platformservice/v1/users//applications-96",
    "sampleCount" : 1,
    "errorCount" : 1,
    "errorPct" : 100.0,
    "meanResTime" : 17.0,
    "medianResTime" : 17.0,
    "minResTime" : 17.0,
    "maxResTime" : 17.0,
    "pct1ResTime" : 17.0,
    "pct2ResTime" : 17.0,
    "pct3ResTime" : 17.0,
    "throughput" : 58.8235294117647,
    "receivedKBytesPerSec" : 24.06939338235294,
    "sentKBytesPerSec" : 25.85018382352941
  },
  "/dashboardservice/v1/dashboard//applications-94" : {
    "transaction" : "/dashboardservice/v1/dashboard//applications-94",
    "sampleCount" : 1,
    "errorCount" : 1,
    "errorPct" : 100.0,
    "meanResTime" : 12.0,
    "medianResTime" : 12.0,
    "minResTime" : 12.0,
    "maxResTime" : 12.0,
    "pct1ResTime" : 12.0,
    "pct2ResTime" : 12.0,
    "pct3ResTime" : 12.0,
    "throughput" : 83.33333333333333,
    "receivedKBytesPerSec" : 34.098307291666664,
    "sentKBytesPerSec" : 35.563151041666664
  },
  "/autopilot/api/v1/getClusterTags-110" : {
    "transaction" : "/autopilot/api/v1/getClusterTags-110",
    "sampleCount" : 1,
    "errorCount" : 1,
    "errorPct" : 100.0,
    "meanResTime" : 22.0,
    "medianResTime" : 22.0,
    "minResTime" : 22.0,
    "maxResTime" : 22.0,
    "pct1ResTime" : 22.0,
    "pct2ResTime" : 22.0,
    "pct3ResTime" : 22.0,
    "throughput" : 45.45454545454545,
    "receivedKBytesPerSec" : 18.599076704545457,
    "sentKBytesPerSec" : 19.309303977272727
  },
  "/autopilot/api/v1/credentials-39" : {
    "transaction" : "/autopilot/api/v1/credentials-39",
    "sampleCount" : 1,
    "errorCount" : 1,
    "errorPct" : 100.0,
    "meanResTime" : 22.0,
    "medianResTime" : 22.0,
    "minResTime" : 22.0,
    "maxResTime" : 22.0,
    "pct1ResTime" : 22.0,
    "pct2ResTime" : 22.0,
    "pct3ResTime" : 22.0,
    "throughput" : 45.45454545454545,
    "receivedKBytesPerSec" : 18.599076704545457,
    "sentKBytesPerSec" : 19.087357954545457
  },
  "/auth/user-44" : {
    "transaction" : "/auth/user-44",
    "sampleCount" : 1,
    "errorCount" : 0,
    "errorPct" : 0.0,
    "meanResTime" : 59.0,
    "medianResTime" : 59.0,
    "minResTime" : 59.0,
    "maxResTime" : 59.0,
    "pct1ResTime" : 59.0,
    "pct2ResTime" : 59.0,
    "pct3ResTime" : 59.0,
    "throughput" : 16.949152542372882,
    "receivedKBytesPerSec" : 16.816737288135595,
    "sentKBytesPerSec" : 7.64698093220339
  },
  "/oes/accountsConfig/getDockerAccounts-107" : {
    "transaction" : "/oes/accountsConfig/getDockerAccounts-107",
    "sampleCount" : 1,
    "errorCount" : 1,
    "errorPct" : 100.0,
    "meanResTime" : 7.0,
    "medianResTime" : 7.0,
    "minResTime" : 7.0,
    "maxResTime" : 7.0,
    "pct1ResTime" : 7.0,
    "pct2ResTime" : 7.0,
    "pct3ResTime" : 7.0,
    "throughput" : 142.85714285714286,
    "receivedKBytesPerSec" : 58.45424107142857,
    "sentKBytesPerSec" : 61.38392857142857
  },
  "/dashboardservice/v1/datasources-68" : {
    "transaction" : "/dashboardservice/v1/datasources-68",
    "sampleCount" : 1,
    "errorCount" : 0,
    "errorPct" : 0.0,
    "meanResTime" : 68.0,
    "medianResTime" : 68.0,
    "minResTime" : 68.0,
    "maxResTime" : 68.0,
    "pct1ResTime" : 68.0,
    "pct2ResTime" : 68.0,
    "pct3ResTime" : 68.0,
    "throughput" : 14.705882352941176,
    "receivedKBytesPerSec" : 23.82525275735294,
    "sentKBytesPerSec" : 6.950827205882352
  },
  "/dashboardservice/v1/applications/14-130" : {
    "transaction" : "/dashboardservice/v1/applications/14-130",
    "sampleCount" : 1,
    "errorCount" : 1,
    "errorPct" : 100.0,
    "meanResTime" : 21.0,
    "medianResTime" : 21.0,
    "minResTime" : 21.0,
    "maxResTime" : 21.0,
    "pct1ResTime" : 21.0,
    "pct2ResTime" : 21.0,
    "pct3ResTime" : 21.0,
    "throughput" : 47.61904761904761,
    "receivedKBytesPerSec" : 19.484747023809522,
    "sentKBytesPerSec" : 20.414806547619047
  },
  "/oes/dashboard/dynamicMenu-63" : {
    "transaction" : "/oes/dashboard/dynamicMenu-63",
    "sampleCount" : 1,
    "errorCount" : 0,
    "errorPct" : 0.0,
    "meanResTime" : 162.0,
    "medianResTime" : 162.0,
    "minResTime" : 162.0,
    "maxResTime" : 162.0,
    "pct1ResTime" : 162.0,
    "pct2ResTime" : 162.0,
    "pct3ResTime" : 162.0,
    "throughput" : 6.172839506172839,
    "receivedKBytesPerSec" : 6.926359953703703,
    "sentKBytesPerSec" : 2.8814621913580245
  },
  "login and Loading" : {
    "transaction" : "login and Loading",
    "sampleCount" : 1,
    "errorCount" : 0,
    "errorPct" : 0.0,
    "meanResTime" : 5503.0,
    "medianResTime" : 5503.0,
    "minResTime" : 5503.0,
    "maxResTime" : 5503.0,
    "pct1ResTime" : 5503.0,
    "pct2ResTime" : 5503.0,
    "pct3ResTime" : 5503.0,
    "throughput" : 0.1817190623296384,
    "receivedKBytesPerSec" : 3.577416579592949,
    "sentKBytesPerSec" : 1.140180640105397
  },
  "/login-59" : {
    "transaction" : "/login-59",
    "sampleCount" : 1,
    "errorCount" : 0,
    "errorPct" : 0.0,
    "meanResTime" : 317.0,
    "medianResTime" : 317.0,
    "minResTime" : 317.0,
    "maxResTime" : 317.0,
    "pct1ResTime" : 317.0,
    "pct2ResTime" : 317.0,
    "pct3ResTime" : 317.0,
    "throughput" : 3.1545741324921135,
    "receivedKBytesPerSec" : 2.42446273659306,
    "sentKBytesPerSec" : 1.7559641167192428
  },
  "/oes/accountsConfig/getAccounts-48-0" : {
    "transaction" : "/oes/accountsConfig/getAccounts-48-0",
    "sampleCount" : 1,
    "errorCount" : 0,
    "errorPct" : 0.0,
    "meanResTime" : 31.0,
    "medianResTime" : 31.0,
    "minResTime" : 31.0,
    "maxResTime" : 31.0,
    "pct1ResTime" : 31.0,
    "pct2ResTime" : 31.0,
    "pct3ResTime" : 31.0,
    "throughput" : 32.25806451612903,
    "receivedKBytesPerSec" : 23.090977822580644,
    "sentKBytesPerSec" : 13.041834677419354
  },
  "/oes/accountsConfig/getAccounts-48-1" : {
    "transaction" : "/oes/accountsConfig/getAccounts-48-1",
    "sampleCount" : 1,
    "errorCount" : 0,
    "errorPct" : 0.0,
    "meanResTime" : 29.0,
    "medianResTime" : 29.0,
    "minResTime" : 29.0,
    "maxResTime" : 29.0,
    "pct1ResTime" : 29.0,
    "pct2ResTime" : 29.0,
    "pct3ResTime" : 29.0,
    "throughput" : 34.48275862068965,
    "receivedKBytesPerSec" : 47.81788793103448,
    "sentKBytesPerSec" : 13.099407327586206
  },
  "/dashboardservice/v1/dashboard/user2/applications-48" : {
    "transaction" : "/dashboardservice/v1/dashboard/user2/applications-48",
    "sampleCount" : 1,
    "errorCount" : 0,
    "errorPct" : 0.0,
    "meanResTime" : 255.0,
    "medianResTime" : 255.0,
    "minResTime" : 255.0,
    "maxResTime" : 255.0,
    "pct1ResTime" : 255.0,
    "pct2ResTime" : 255.0,
    "pct3ResTime" : 255.0,
    "throughput" : 3.9215686274509802,
    "receivedKBytesPerSec" : 5.013020833333333,
    "sentKBytesPerSec" : 1.9186580882352942
  },
  "/platformservice/v1/users/user2/usergroups/refresh-45" : {
    "transaction" : "/platformservice/v1/users/user2/usergroups/refresh-45",
    "sampleCount" : 1,
    "errorCount" : 0,
    "errorPct" : 0.0,
    "meanResTime" : 60.0,
    "medianResTime" : 60.0,
    "minResTime" : 60.0,
    "maxResTime" : 60.0,
    "pct1ResTime" : 60.0,
    "pct2ResTime" : 60.0,
    "pct3ResTime" : 60.0,
    "throughput" : 16.666666666666668,
    "receivedKBytesPerSec" : 12.125651041666668,
    "sentKBytesPerSec" : 9.033203125
  },
  "/dashboardservice/v1/installation/installationmode-64" : {
    "transaction" : "/dashboardservice/v1/installation/installationmode-64",
    "sampleCount" : 1,
    "errorCount" : 0,
    "errorPct" : 0.0,
    "meanResTime" : 36.0,
    "medianResTime" : 36.0,
    "minResTime" : 36.0,
    "maxResTime" : 36.0,
    "pct1ResTime" : 36.0,
    "pct2ResTime" : 36.0,
    "pct3ResTime" : 36.0,
    "throughput" : 27.777777777777775,
    "receivedKBytesPerSec" : 21.94552951388889,
    "sentKBytesPerSec" : 13.617621527777779
  },
  "/platformservice/v1/users//usergroups/refresh-92" : {
    "transaction" : "/platformservice/v1/users//usergroups/refresh-92",
    "sampleCount" : 1,
    "errorCount" : 1,
    "errorPct" : 100.0,
    "meanResTime" : 4.0,
    "medianResTime" : 4.0,
    "minResTime" : 4.0,
    "maxResTime" : 4.0,
    "pct1ResTime" : 4.0,
    "pct2ResTime" : 4.0,
    "pct3ResTime" : 4.0,
    "throughput" : 250.0,
    "receivedKBytesPerSec" : 102.294921875,
    "sentKBytesPerSec" : 119.873046875
  },
  "/oes/accountsConfig/saveAccount-77" : {
    "transaction" : "/oes/accountsConfig/saveAccount-77",
    "sampleCount" : 1,
    "errorCount" : 1,
    "errorPct" : 100.0,
    "meanResTime" : 56.0,
    "medianResTime" : 56.0,
    "minResTime" : 56.0,
    "maxResTime" : 56.0,
    "pct1ResTime" : 56.0,
    "pct2ResTime" : 56.0,
    "pct3ResTime" : 56.0,
    "throughput" : 17.857142857142858,
    "receivedKBytesPerSec" : 19.287109375,
    "sentKBytesPerSec" : 11.928013392857142
  },
  "/oes/accountsConfig/saveAccount-76" : {
    "transaction" : "/oes/accountsConfig/saveAccount-76",
    "sampleCount" : 1,
    "errorCount" : 0,
    "errorPct" : 0.0,
    "meanResTime" : 18.0,
    "medianResTime" : 18.0,
    "minResTime" : 18.0,
    "maxResTime" : 18.0,
    "pct1ResTime" : 18.0,
    "pct2ResTime" : 18.0,
    "pct3ResTime" : 18.0,
    "throughput" : 55.55555555555555,
    "receivedKBytesPerSec" : 37.05512152777778,
    "sentKBytesPerSec" : 29.568142361111114
  },
  "/dashboardservice/v1/datasources-51" : {
    "transaction" : "/dashboardservice/v1/datasources-51",
    "sampleCount" : 1,
    "errorCount" : 0,
    "errorPct" : 0.0,
    "meanResTime" : 77.0,
    "medianResTime" : 77.0,
    "minResTime" : 77.0,
    "maxResTime" : 77.0,
    "pct1ResTime" : 77.0,
    "pct2ResTime" : 77.0,
    "pct3ResTime" : 77.0,
    "throughput" : 12.987012987012989,
    "receivedKBytesPerSec" : 20.977069805194805,
    "sentKBytesPerSec" : 6.138392857142858
  },
  "/login-42" : {
    "transaction" : "/login-42",
    "sampleCount" : 1,
    "errorCount" : 0,
    "errorPct" : 0.0,
    "meanResTime" : 398.0,
    "medianResTime" : 398.0,
    "minResTime" : 398.0,
    "maxResTime" : 398.0,
    "pct1ResTime" : 398.0,
    "pct2ResTime" : 398.0,
    "pct3ResTime" : 398.0,
    "throughput" : 2.512562814070352,
    "receivedKBytesPerSec" : 1.9187735552763818,
    "sentKBytesPerSec" : 1.3863261620603013
  },
  "/oes/dashboard/widgetRawData-49" : {
    "transaction" : "/oes/dashboard/widgetRawData-49",
    "sampleCount" : 1,
    "errorCount" : 0,
    "errorPct" : 0.0,
    "meanResTime" : 74.0,
    "medianResTime" : 74.0,
    "minResTime" : 74.0,
    "maxResTime" : 74.0,
    "pct1ResTime" : 74.0,
    "pct2ResTime" : 74.0,
    "pct3ResTime" : 74.0,
    "throughput" : 13.513513513513514,
    "receivedKBytesPerSec" : 13.803842905405405,
    "sentKBytesPerSec" : 6.33445945945946
  },
  "/dashboardservice/v1/applications/17-321" : {
    "transaction" : "/dashboardservice/v1/applications/17-321",
    "sampleCount" : 1,
    "errorCount" : 1,
    "errorPct" : 100.0,
    "meanResTime" : 10.0,
    "medianResTime" : 10.0,
    "minResTime" : 10.0,
    "maxResTime" : 10.0,
    "pct1ResTime" : 10.0,
    "pct2ResTime" : 10.0,
    "pct3ResTime" : 10.0,
    "throughput" : 100.0,
    "receivedKBytesPerSec" : 40.91796875,
    "sentKBytesPerSec" : 43.5546875
  },
  "/platformservice/v1/applications-50" : {
    "transaction" : "/platformservice/v1/applications-50",
    "sampleCount" : 1,
    "errorCount" : 0,
    "errorPct" : 0.0,
    "meanResTime" : 50.0,
    "medianResTime" : 50.0,
    "minResTime" : 50.0,
    "maxResTime" : 50.0,
    "pct1ResTime" : 50.0,
    "pct2ResTime" : 50.0,
    "pct3ResTime" : 50.0,
    "throughput" : 20.0,
    "receivedKBytesPerSec" : 23.14453125,
    "sentKBytesPerSec" : 9.453125
  },
  "Login and Loading" : {
    "transaction" : "Login and Loading",
    "sampleCount" : 1,
    "errorCount" : 0,
    "errorPct" : 0.0,
    "meanResTime" : 6265.0,
    "medianResTime" : 6265.0,
    "minResTime" : 6265.0,
    "maxResTime" : 6265.0,
    "pct1ResTime" : 6265.0,
    "pct2ResTime" : 6265.0,
    "pct3ResTime" : 6265.0,
    "throughput" : 0.15961691939345568,
    "receivedKBytesPerSec" : 3.4270874900239425,
    "sentKBytesPerSec" : 1.1547286512370312
  },
  "/oes/accountsConfig/getAccounts-78" : {
    "transaction" : "/oes/accountsConfig/getAccounts-78",
    "sampleCount" : 1,
    "errorCount" : 0,
    "errorPct" : 0.0,
    "meanResTime" : 36.0,
    "medianResTime" : 36.0,
    "minResTime" : 36.0,
    "maxResTime" : 36.0,
    "pct1ResTime" : 36.0,
    "pct2ResTime" : 36.0,
    "pct3ResTime" : 36.0,
    "throughput" : 27.777777777777775,
    "receivedKBytesPerSec" : 28.04904513888889,
    "sentKBytesPerSec" : 13.237847222222223
  },
  "/dashboardservice/v1/application/36-43" : {
    "transaction" : "/dashboardservice/v1/application/36-43",
    "sampleCount" : 1,
    "errorCount" : 1,
    "errorPct" : 100.0,
    "meanResTime" : 21.0,
    "medianResTime" : 21.0,
    "minResTime" : 21.0,
    "maxResTime" : 21.0,
    "pct1ResTime" : 21.0,
    "pct2ResTime" : 21.0,
    "pct3ResTime" : 21.0,
    "throughput" : 47.61904761904761,
    "receivedKBytesPerSec" : 19.484747023809522,
    "sentKBytesPerSec" : 24.693080357142854
  },
  "/dashboardservice/v1/application/36-42" : {
    "transaction" : "/dashboardservice/v1/application/36-42",
    "sampleCount" : 1,
    "errorCount" : 1,
    "errorPct" : 100.0,
    "meanResTime" : 10.0,
    "medianResTime" : 10.0,
    "minResTime" : 10.0,
    "maxResTime" : 10.0,
    "pct1ResTime" : 10.0,
    "pct2ResTime" : 10.0,
    "pct3ResTime" : 10.0,
    "throughput" : 100.0,
    "receivedKBytesPerSec" : 40.91796875,
    "sentKBytesPerSec" : 44.7265625
  },
  "/oes/accountsConfig/getAccounts-74" : {
    "transaction" : "/oes/accountsConfig/getAccounts-74",
    "sampleCount" : 1,
    "errorCount" : 0,
    "errorPct" : 0.0,
    "meanResTime" : 97.0,
    "medianResTime" : 97.0,
    "minResTime" : 97.0,
    "maxResTime" : 97.0,
    "pct1ResTime" : 97.0,
    "pct2ResTime" : 97.0,
    "pct3ResTime" : 97.0,
    "throughput" : 10.309278350515465,
    "receivedKBytesPerSec" : 10.409954896907216,
    "sentKBytesPerSec" : 4.933150773195877
  },
  "/oes/dashboard/widgetRawData-66" : {
    "transaction" : "/oes/dashboard/widgetRawData-66",
    "sampleCount" : 1,
    "errorCount" : 0,
    "errorPct" : 0.0,
    "meanResTime" : 63.0,
    "medianResTime" : 63.0,
    "minResTime" : 63.0,
    "maxResTime" : 63.0,
    "pct1ResTime" : 63.0,
    "pct2ResTime" : 63.0,
    "pct3ResTime" : 63.0,
    "throughput" : 15.873015873015872,
    "receivedKBytesPerSec" : 16.2140376984127,
    "sentKBytesPerSec" : 7.440476190476191
  },
  "/auth/user-61" : {
    "transaction" : "/auth/user-61",
    "sampleCount" : 1,
    "errorCount" : 0,
    "errorPct" : 0.0,
    "meanResTime" : 36.0,
    "medianResTime" : 36.0,
    "minResTime" : 36.0,
    "maxResTime" : 36.0,
    "pct1ResTime" : 36.0,
    "pct2ResTime" : 36.0,
    "pct3ResTime" : 36.0,
    "throughput" : 27.777777777777775,
    "receivedKBytesPerSec" : 27.56076388888889,
    "sentKBytesPerSec" : 12.532552083333334
  },
  "/platformservice/v1/applications-67" : {
    "transaction" : "/platformservice/v1/applications-67",
    "sampleCount" : 1,
    "errorCount" : 0,
    "errorPct" : 0.0,
    "meanResTime" : 65.0,
    "medianResTime" : 65.0,
    "minResTime" : 65.0,
    "maxResTime" : 65.0,
    "pct1ResTime" : 65.0,
    "pct2ResTime" : 65.0,
    "pct3ResTime" : 65.0,
    "throughput" : 15.384615384615385,
    "receivedKBytesPerSec" : 17.803485576923077,
    "sentKBytesPerSec" : 7.271634615384615
  },
  "/platformservice/v1/usergroups-103" : {
    "transaction" : "/platformservice/v1/usergroups-103",
    "sampleCount" : 1,
    "errorCount" : 1,
    "errorPct" : 100.0,
    "meanResTime" : 15.0,
    "medianResTime" : 15.0,
    "minResTime" : 15.0,
    "maxResTime" : 15.0,
    "pct1ResTime" : 15.0,
    "pct2ResTime" : 15.0,
    "pct3ResTime" : 15.0,
    "throughput" : 66.66666666666667,
    "receivedKBytesPerSec" : 27.278645833333336,
    "sentKBytesPerSec" : 27.604166666666668
  },
  "/oes/appOnboarding/images-126" : {
    "transaction" : "/oes/appOnboarding/images-126",
    "sampleCount" : 1,
    "errorCount" : 1,
    "errorPct" : 100.0,
    "meanResTime" : 18.0,
    "medianResTime" : 18.0,
    "minResTime" : 18.0,
    "maxResTime" : 18.0,
    "pct1ResTime" : 18.0,
    "pct2ResTime" : 18.0,
    "pct3ResTime" : 18.0,
    "throughput" : 55.55555555555555,
    "receivedKBytesPerSec" : 22.732204861111114,
    "sentKBytesPerSec" : 24.522569444444446
  },
  "/dashboardservice/v1/dashboard//applications-45" : {
    "transaction" : "/dashboardservice/v1/dashboard//applications-45",
    "sampleCount" : 1,
    "errorCount" : 1,
    "errorPct" : 100.0,
    "meanResTime" : 9.0,
    "medianResTime" : 9.0,
    "minResTime" : 9.0,
    "maxResTime" : 9.0,
    "pct1ResTime" : 9.0,
    "pct2ResTime" : 9.0,
    "pct3ResTime" : 9.0,
    "throughput" : 111.1111111111111,
    "receivedKBytesPerSec" : 45.46440972222223,
    "sentKBytesPerSec" : 48.177083333333336
  },
  "/platformservice/v1/users/user2/usergroups/refresh-62" : {
    "transaction" : "/platformservice/v1/users/user2/usergroups/refresh-62",
    "sampleCount" : 1,
    "errorCount" : 0,
    "errorPct" : 0.0,
    "meanResTime" : 67.0,
    "medianResTime" : 67.0,
    "minResTime" : 67.0,
    "maxResTime" : 67.0,
    "pct1ResTime" : 67.0,
    "pct2ResTime" : 67.0,
    "pct3ResTime" : 67.0,
    "throughput" : 14.925373134328359,
    "receivedKBytesPerSec" : 10.85879197761194,
    "sentKBytesPerSec" : 8.089435634328357
  },
  "/oes/dashboard/applications/jmetertest/releases-328" : {
    "transaction" : "/oes/dashboard/applications/jmetertest/releases-328",
    "sampleCount" : 1,
    "errorCount" : 1,
    "errorPct" : 100.0,
    "meanResTime" : 18.0,
    "medianResTime" : 18.0,
    "minResTime" : 18.0,
    "maxResTime" : 18.0,
    "pct1ResTime" : 18.0,
    "pct2ResTime" : 18.0,
    "pct3ResTime" : 18.0,
    "throughput" : 55.55555555555555,
    "receivedKBytesPerSec" : 22.732204861111114,
    "sentKBytesPerSec" : 23.980034722222225
  },
  "/oes/audit/pipelinescount-98" : {
    "transaction" : "/oes/audit/pipelinescount-98",
    "sampleCount" : 1,
    "errorCount" : 1,
    "errorPct" : 100.0,
    "meanResTime" : 4.0,
    "medianResTime" : 4.0,
    "minResTime" : 4.0,
    "maxResTime" : 4.0,
    "pct1ResTime" : 4.0,
    "pct2ResTime" : 4.0,
    "pct3ResTime" : 4.0,
    "throughput" : 250.0,
    "receivedKBytesPerSec" : 102.294921875,
    "sentKBytesPerSec" : 102.294921875
  },
  "/dashboardservice/v1/applications/jmetertest" : {
    "transaction" : "/dashboardservice/v1/applications/jmetertest",
    "sampleCount" : 1,
    "errorCount" : 1,
    "errorPct" : 100.0,
    "meanResTime" : 27.0,
    "medianResTime" : 27.0,
    "minResTime" : 27.0,
    "maxResTime" : 27.0,
    "pct1ResTime" : 27.0,
    "pct2ResTime" : 27.0,
    "pct3ResTime" : 27.0,
    "throughput" : 37.03703703703704,
    "receivedKBytesPerSec" : 15.15480324074074,
    "sentKBytesPerSec" : 15.87818287037037
  },
  "/oes/audit/pipelineconfig-99" : {
    "transaction" : "/oes/audit/pipelineconfig-99",
    "sampleCount" : 1,
    "errorCount" : 1,
    "errorPct" : 100.0,
    "meanResTime" : 17.0,
    "medianResTime" : 17.0,
    "minResTime" : 17.0,
    "maxResTime" : 17.0,
    "pct1ResTime" : 17.0,
    "pct2ResTime" : 17.0,
    "pct3ResTime" : 17.0,
    "throughput" : 58.8235294117647,
    "receivedKBytesPerSec" : 24.06939338235294,
    "sentKBytesPerSec" : 24.988511029411764
  },
  "/platformservice/v1/permissions-104" : {
    "transaction" : "/platformservice/v1/permissions-104",
    "sampleCount" : 1,
    "errorCount" : 1,
    "errorPct" : 100.0,
    "meanResTime" : 13.0,
    "medianResTime" : 13.0,
    "minResTime" : 13.0,
    "maxResTime" : 13.0,
    "pct1ResTime" : 13.0,
    "pct2ResTime" : 13.0,
    "pct3ResTime" : 13.0,
    "throughput" : 76.92307692307693,
    "receivedKBytesPerSec" : 31.475360576923077,
    "sentKBytesPerSec" : 31.926081730769234
  },
  "Debug Sampler" : {
    "transaction" : "Debug Sampler",
    "sampleCount" : 1,
    "errorCount" : 0,
    "errorPct" : 0.0,
    "meanResTime" : 1.0,
    "medianResTime" : 1.0,
    "minResTime" : 1.0,
    "maxResTime" : 1.0,
    "pct1ResTime" : 1.0,
    "pct2ResTime" : 1.0,
    "pct3ResTime" : 1.0,
    "throughput" : 1000.0,
    "receivedKBytesPerSec" : 422.8515625,
    "sentKBytesPerSec" : 0.0
  },
  "Total" : {
    "transaction" : "Total",
    "sampleCount" : 92,
    "errorCount" : 54,
    "errorPct" : 58.695652,
    "meanResTime" : 142.83695652173913,
    "medianResTime" : 21.0,
    "minResTime" : 1.0,
    "maxResTime" : 4687.0,
    "pct1ResTime" : 146.5000000000001,
    "pct2ResTime" : 326.79999999999984,
    "pct3ResTime" : 4687.0,
    "throughput" : 2.4187611736249868,
    "receivedKBytesPerSec" : 1.9818036284703964,
    "sentKBytesPerSec" : 1.1247311346487538
  },
  "/autopilot/api/v1/credentials-132" : {
    "transaction" : "/autopilot/api/v1/credentials-132",
    "sampleCount" : 1,
    "errorCount" : 1,
    "errorPct" : 100.0,
    "meanResTime" : 38.0,
    "medianResTime" : 38.0,
    "minResTime" : 38.0,
    "maxResTime" : 38.0,
    "pct1ResTime" : 38.0,
    "pct2ResTime" : 38.0,
    "pct3ResTime" : 38.0,
    "throughput" : 26.31578947368421,
    "receivedKBytesPerSec" : 10.767886513157896,
    "sentKBytesPerSec" : 11.101973684210527
  },
  "/autopilot/api/v1/credentials-135" : {
    "transaction" : "/autopilot/api/v1/credentials-135",
    "sampleCount" : 1,
    "errorCount" : 1,
    "errorPct" : 100.0,
    "meanResTime" : 18.0,
    "medianResTime" : 18.0,
    "minResTime" : 18.0,
    "maxResTime" : 18.0,
    "pct1ResTime" : 18.0,
    "pct2ResTime" : 18.0,
    "pct3ResTime" : 18.0,
    "throughput" : 55.55555555555555,
    "receivedKBytesPerSec" : 22.732204861111114,
    "sentKBytesPerSec" : 22.94921875
  },
  "/oes/accountsConfig/getAccounts-325" : {
    "transaction" : "/oes/accountsConfig/getAccounts-325",
    "sampleCount" : 1,
    "errorCount" : 1,
    "errorPct" : 100.0,
    "meanResTime" : 16.0,
    "medianResTime" : 16.0,
    "minResTime" : 16.0,
    "maxResTime" : 16.0,
    "pct1ResTime" : 16.0,
    "pct2ResTime" : 16.0,
    "pct3ResTime" : 16.0,
    "throughput" : 62.5,
    "receivedKBytesPerSec" : 25.57373046875,
    "sentKBytesPerSec" : 25.93994140625
  }
}